{
"r2AccountId": "db679700d3a9fd8df9f885a8603443f6",

"r2AccessKeyId" : "25deee76eb632ce7a8e37734a0cdb12f",

"r2SecretAccessKey" : "59148019a2d09713bba8afcf0eaca9f198f577bb29aefb48a6437b3e9c197614",

"r2BucketName" : "databmrp",

"ipServer1": "191.96.224.79:8397",

"ipServer2": "191.96.224.79:8397",

"bannerLink" : " ",

"bannerImg" : " ",

"appInstagramLink" : "https://www.instagram.com/ares_basilioo?igsh=bXI4NXd3MnhvMGJi",

"appSiteLink": "https://baixar-rise-nation.my.canva.site/ofc",

"appDiscordLink": "https://discord.gg/cEskKqhjY8",

"appYoutubeLink": "https://youtube.com/@playzone_rp?si=72zziDnbRg33FrNp",

"appTiktokLink": " "

}
